pne/__init__.py
pne-1.1.1.dist-info/LICENSE
pne-1.1.1.dist-info/METADATA
pne-1.1.1.dist-info/WHEEL
pne-1.1.1.dist-info/RECORD
