Metadata-Version: 2.1
Name: pne
Version: 1.1.1
Summary: 🚀 Simplified promptulate call. Now you can use `import pne` to call promptulate.
Home-page: https://github.com/Undertone0809/pne
License: Apache Software License 2.0
Keywords: promptulate,pne,prompt,agent,openai,chatgpt,gpt,llm,openai,langchain,litellm
Author: Undertone0809
Author-email: zeeland4work@gmail.com
Requires-Python: >=3.8.1,<4.0
Classifier: License :: Other/Proprietary License
Classifier: Programming Language :: Python :: 3
Classifier: Programming Language :: Python :: 3.9
Classifier: Programming Language :: Python :: 3.10
Classifier: Programming Language :: Python :: 3.11
Classifier: Programming Language :: Python :: 3.12
Requires-Dist: promptulate (>=1.16.6,<2.0.0)
Project-URL: Repository, https://github.com/Undertone0809/pne
